torchdraw/__init__.py
torchdraw/coordinate_conversion.py
torchdraw/lines.py
torchdraw/points.py
torchdraw/rendering.py
torchdraw/types.py
torchdraw-0.0.1.dist-info/METADATA
torchdraw-0.0.1.dist-info/WHEEL
torchdraw-0.0.1.dist-info/licenses/LICENSE
torchdraw-0.0.1.dist-info/RECORD
