Metadata-Version: 2.3
Name: torchdraw
Version: 0.0.1
Summary: PyTorch-based drawing code for points and lines.
Project-URL: repository, https://github.com/dcharatan/torchdraw
Author-email: David Charatan <charatan@mit.edu>
License: MIT License
Keywords: drawing,pytorch
Classifier: Development Status :: 3 - Alpha
Classifier: Intended Audience :: Developers
Classifier: Intended Audience :: Financial and Insurance Industry
Classifier: Intended Audience :: Information Technology
Classifier: Intended Audience :: Science/Research
Classifier: License :: OSI Approved :: MIT License
Classifier: Natural Language :: English
Classifier: Programming Language :: Python :: 3
Classifier: Topic :: Scientific/Engineering :: Artificial Intelligence
Classifier: Topic :: Scientific/Engineering :: Information Analysis
Classifier: Topic :: Scientific/Engineering :: Mathematics
Requires-Python: ~=3.11
Requires-Dist: beartype>=0.17.2
Requires-Dist: einops>=0.8.0
Requires-Dist: jaxtyping>=0.2.28
Requires-Dist: numpy>=1.20.0
Requires-Dist: torch>=2.0.0
